{"changeList":[{"Id":"8faf52cb-c244-4e7e-b526-c40cc17c02c4","ApiChange":"Resource","ChangedApiName":"authenticationRequirement","ChangeType":"Deletion","Description":"Removed the **authenticationRequirement** resource type *@&*"},{"Id":"33bf8a68-2c74-4834-8beb-ba38b294d981","ApiChange":"Resource","ChangedApiName":"riskEventTypes_v2","ChangeType":"Deletion","Description":"Removed the **riskEventTypes_v2** resource type *@&*"},{"Id":"3308f984-fd3e-475b-b4de-2523abd0f0da","ApiChange":"Resource","ChangedApiName":"servicePrincipal","ChangeType":"Deletion","Description":"Removed the **servicePrincipal** resource type *@&*"},{"Id":"aec46e35-7f18-4bf8-9da6-97a39e1cce4c","ApiChange":"Resource","ChangedApiName":"provisioningServicePrincipal","ChangeType":"Deletion","Description":"Removed the **provisioningServicePrincipal** resource type"}],"Id":null,"CreatedBy":null,"Cloud":"prd","Version":"beta","CreatedDateTime":"2020-04-03T05:37:39.5116778Z","DocPRUrl":null,"WorkloadArea":"Identity and access (Azure AD)"}